CHANGES
CONTRIBUTING.md
LICENSE
MANIFEST.in
README.rst
pyproject.toml
setup.py
curio/__init__.py
curio/__main__.py
curio/channel.py
curio/debug.py
curio/errors.py
curio/file.py
curio/io.py
curio/kernel.py
curio/meta.py
curio/monitor.py
curio/network.py
curio/queue.py
curio/sched.py
curio/socket.py
curio/ssl.py
curio/sync.py
curio/task.py
curio/thread.py
curio/time.py
curio/timequeue.py
curio/traps.py
curio/workers.py
curio_compat.egg-info/PKG-INFO
curio_compat.egg-info/SOURCES.txt
curio_compat.egg-info/dependency_links.txt
curio_compat.egg-info/requires.txt
curio_compat.egg-info/top_level.txt
docs/Makefile
docs/conf.py
docs/customization.py
docs/howto.rst
docs/index.rst
docs/make.bat
docs/reference.rst
docs/tutorial.rst
docs/_static/curiolayer.png
docs/_static/guiserv.png
docs/_static/layers.png
examples/boundsema.py
examples/chat.py
examples/curio_subprocess.py
examples/curio_zmq.py
examples/dualserv.py
examples/echoserv.py
examples/echoserv2.py
examples/echoserv3.py
examples/fibserve.py
examples/guiserv.py
examples/guiserv2.py
examples/happy.py
examples/pinger.py
examples/prodcons.py
examples/promise.py
examples/pytest_plugin.py
examples/signal_handling.py
examples/ssl_conn.py
examples/ssl_echo.py
examples/ssl_echo_client.py
examples/ssl_http.py
examples/ssl_test.crt
examples/ssl_test_readme.txt
examples/ssl_test_rsa
examples/udp_echo.py
examples/udp_echo_client.py
examples/unix_echo.py
examples/unix_echo_client.py
examples/ws_server.py
examples/zmq_puller.py
examples/zmq_pusher.py
examples/zmq_rpcclient.py
examples/zmq_rpcserv.py
examples/bench/asyncecho.py
examples/bench/asyncproto.py
examples/bench/asyncsslecho.py
examples/bench/asyncstream.py
examples/bench/client.c
examples/bench/client.py
examples/bench/curioecho.py
examples/bench/curiosslecho.py
examples/bench/curiosslstream.py
examples/bench/curiostream.py
examples/bench/echoclient.py
examples/bench/gevecho.py
examples/bench/gevsslecho.py
examples/bench/nodeecho.js
examples/bench/process_perf.py
examples/bench/ssl_test.crt
examples/bench/ssl_test_rsa
examples/bench/sslclient.py
examples/bench/subproc_perf.py
examples/bench/thread_perf.py
examples/bench/threadecho.py
