Metadata-Version: 2.1
Name: curio-compat
Version: 1.6.6
Summary: Curio is a coroutine-based library for concurrent systems programming.
Author-email: David Beazley <dave@dabeaz.com>
License: BSD
Project-URL: homepage, https://github.com/dabeaz/curio
Project-URL: repository, https://github.com/dabeaz/curio
Classifier: Programming Language :: Python :: 3
Classifier: Framework :: Pytest
Requires-Python: >=3.8
License-File: LICENSE
Provides-Extra: test
Requires-Dist: pytest; extra == "test"
Requires-Dist: Sphinx; extra == "test"
Requires-Dist: ruff; extra == "test"
Requires-Dist: mypy; extra == "test"
Requires-Dist: pre-commit; extra == "test"
Requires-Dist: bump2version; extra == "test"
